message_to_request/__init__.py
message_to_request/enums.py
message_to_request/sender.py
message_to_request-0.0.3.dist-info/METADATA
message_to_request-0.0.3.dist-info/WHEEL
message_to_request-0.0.3.dist-info/top_level.txt
message_to_request-0.0.3.dist-info/RECORD
