Metadata-Version: 2.1
Name: message_to_request
Version: 0.0.3
Summary: Библиотека для упаковки текста в http запрос
Author: abirukov
Author-email: abirukov2008@yandex.ru
Project-URL: GitHub, https://github.com/abirukov/message_to_request
Classifier: Programming Language :: Python :: 3.12
Requires-Python: >=3.10
Requires-Dist: httpx
